chercher_plugin_txt/__init__.py
chercher_plugin_txt-0.1.8.dist-info/licenses/LICENSE
chercher_plugin_txt-0.1.8.dist-info/METADATA
chercher_plugin_txt-0.1.8.dist-info/WHEEL
chercher_plugin_txt-0.1.8.dist-info/entry_points.txt
chercher_plugin_txt-0.1.8.dist-info/top_level.txt
chercher_plugin_txt-0.1.8.dist-info/RECORD
