Metadata-Version: 2.4
Name: chercher-plugin-txt
Version: 0.1.8
Summary: Chercher plugin that adds support for plain text files.
Author-email: dnlzrgz <contact@dnlzrgz.com>
License-Expression: MIT
Project-URL: Homepage, https://github.com/dnlzrgz/chercher-plugin-txt
Project-URL: Changelog, https://github.com/dnlzrgz/chercher-plugin-txt/releases
Project-URL: Issues, https://github.com/dnlzrgz/chercher-plugin-txt/issues
Project-URL: CI, https://github.com/dnlzrgz/chercher-plugin-txt/actions
Requires-Python: >=3.13
License-File: LICENSE
Requires-Dist: chercher>=0.1.23
Dynamic: license-file
